monod/__init__.py
monod/analysis.py
monod/cme_toolbox.py
monod/drivers.py
monod/extract_data.py
monod/inference.py
monod/plot_aesthetics.py
monod/preprocess.py
monod-0.2.6.0.dist-info/LICENSE
monod-0.2.6.0.dist-info/METADATA
monod-0.2.6.0.dist-info/WHEEL
monod-0.2.6.0.dist-info/top_level.txt
monod-0.2.6.0.dist-info/RECORD
