Metadata-Version: 2.1
Name: monod
Version: 0.2.6.0
Summary: the Monod package fits CME models to sequencing data.
Home-page: https://github.com/pachterlab/monod
Author: Gennady Gorin, Lior Pachter
Author-email: ggorin@caltech.edu, lpachter@caltech.edu
Classifier: Programming Language :: Python :: 3
Classifier: License :: OSI Approved :: BSD License
Classifier: Operating System :: OS Independent
Requires-Python: >=3.6
License-File: LICENSE
Requires-Dist: numpy
Requires-Dist: scipy
Requires-Dist: numdifftools
Requires-Dist: pytz
Requires-Dist: anndata
Requires-Dist: loompy
